redux/__init__.py
redux/py.typed
redux/slice.py
redux/store.py
redux_toolkit-0.0.1.dist-info/METADATA
redux_toolkit-0.0.1.dist-info/WHEEL
redux_toolkit-0.0.1.dist-info/RECORD
